html_for_nlp/__init__.py
html_for_nlp-0.0.2.dist-info/METADATA
html_for_nlp-0.0.2.dist-info/WHEEL
html_for_nlp-0.0.2.dist-info/top_level.txt
html_for_nlp-0.0.2.dist-info/RECORD
