Metadata-Version: 2.1
Name: html-for-nlp
Version: 0.0.2
Summary: HTML for NLP
Home-page: https://github.com/druskacik/html_for_nlp
Author: Róbert Druska
Author-email: robert.druska@gmail.com
License: MIT
Requires-Dist: beautifulsoup4
Requires-Dist: lxml
